vitosa_speech_II/__init__.py
vitosa_speech_II/audio.py
vitosa_speech_II/inference.py
vitosa_speech_II/model.py
vitosa_speech_II/utils.py
vitosa_speech_ii-0.0.1.dist-info/METADATA
vitosa_speech_ii-0.0.1.dist-info/WHEEL
vitosa_speech_ii-0.0.1.dist-info/top_level.txt
vitosa_speech_ii-0.0.1.dist-info/RECORD
