Metadata-Version: 2.4
Name: vitosa-speech-II
Version: 0.0.1
Summary: A library for Robust Vietnamese Audio-Based Toxic Span Detection and Censoring
Author: Vy Le-Phuong Huynh, Huy Ba Do and Luan Thanh Nguyen
Author-email: luannt@uit.edu.vn
Project-URL: Model (Hugging Face), https://huggingface.co/UIT-ViToSA/PhoWhisper-BiLSTM-CRF
Keywords: audio-processing,toxic-span-detection,vietnamese,asr,speech-recognition,censoring,phowhisper
Classifier: Development Status :: 4 - Beta
Classifier: Intended Audience :: Developers
Classifier: Intended Audience :: Science/Research
Classifier: Programming Language :: Python :: 3
Classifier: Programming Language :: Python :: 3.8
Classifier: Programming Language :: Python :: 3.9
Classifier: Programming Language :: Python :: 3.10
Classifier: License :: OSI Approved :: MIT License
Classifier: Operating System :: OS Independent
Classifier: Topic :: Scientific/Engineering :: Artificial Intelligence
Classifier: Topic :: Multimedia :: Sound/Audio :: Speech
Classifier: Natural Language :: Vietnamese
Requires-Python: >=3.7
Requires-Dist: torch>=1.13.0
Requires-Dist: transformers>=4.28.0
Requires-Dist: librosa
Requires-Dist: pydub
Requires-Dist: huggingface_hub
Requires-Dist: pytorch-crf
Requires-Dist: numpy
Requires-Dist: tqdm
Dynamic: author
Dynamic: author-email
Dynamic: classifier
Dynamic: description
Dynamic: description-content-type
Dynamic: keywords
Dynamic: project-url
Dynamic: requires-dist
Dynamic: requires-python
Dynamic: summary
